{
	"$schema": "https://raw.githubusercontent.com/JanDeDobbeleer/oh-my-posh/main/themes/schema.json",
	"blocks": [
		{
			"alignment": "left",
			"segments": [
				{
					"background": "#61AFEF",
					"foreground": "#ffffff",
					"leading_diamond": "",
					"style": "diamond",
					"template": " {{ .UserName }}@{{ .HostName }} ",
					"trailing_diamond": "",
					"type": "session"
				},
				{
					"background": "#C678DD",
					"foreground": "#ffffff",
					"powerline_symbol": "",
					"properties": {
						"style": "full"
					},
					"style": "powerline",
					"template": " {{ .Path }} ",
					"type": "path"
				},
				{
					"background": "#95ffa4",
					"foreground": "#193549",
					"powerline_symbol": "",
					"style": "powerline",
					"template": " {{ .HEAD }} ",
					"type": "git"
				},
				{
					"background": "#FF6471",
					"foreground": "#ffffff",
					"leading_diamond": "<transparent,background></>",
					"style": "diamond",
					"template": " {{ if .Error }}{{ .Error }}{{ else }}{{ if .Venv }}{{ .Venv }} {{ end }}{{ .Full }}{{ end }} ",
					"trailing_diamond": "",
					"type": "python"
				}
			],
			"type": "prompt"
		}
	],
	"final_space": true,
	"version": 2
}
